SklearnYuTensorflowJiqiXuexiShiyongZhinanZhongwenban2018620/README.md
SklearnYuTensorflowJiqiXuexiShiyongZhinanZhongwenban2018620/__init__.py
SklearnYuTensorflowJiqiXuexiShiyongZhinanZhongwenban2018620/__main__.py
SklearnYuTensorflowJiqiXuexiShiyongZhinanZhongwenban2018620/file.epub
SklearnYuTensorflowJiqiXuexiShiyongZhinanZhongwenban2018620/index.html
SklearnYuTensorflowJiqiXuexiShiyongZhinanZhongwenban2018620/css/__init__.py
SklearnYuTensorflowJiqiXuexiShiyongZhinanZhongwenban2018620/css/annotations.css
SklearnYuTensorflowJiqiXuexiShiyongZhinanZhongwenban2018620/css/main.css
SklearnYuTensorflowJiqiXuexiShiyongZhinanZhongwenban2018620/css/normalize.css
SklearnYuTensorflowJiqiXuexiShiyongZhinanZhongwenban2018620/css/popup.css
SklearnYuTensorflowJiqiXuexiShiyongZhinanZhongwenban2018620/font/__init__.py
SklearnYuTensorflowJiqiXuexiShiyongZhinanZhongwenban2018620/font/fontello.eot
SklearnYuTensorflowJiqiXuexiShiyongZhinanZhongwenban2018620/font/fontello.svg
SklearnYuTensorflowJiqiXuexiShiyongZhinanZhongwenban2018620/font/fontello.ttf
SklearnYuTensorflowJiqiXuexiShiyongZhinanZhongwenban2018620/font/fontello.woff
SklearnYuTensorflowJiqiXuexiShiyongZhinanZhongwenban2018620/img/__init__.py
SklearnYuTensorflowJiqiXuexiShiyongZhinanZhongwenban2018620/img/annotator-glyph-sprite.png
SklearnYuTensorflowJiqiXuexiShiyongZhinanZhongwenban2018620/img/annotator-icon-sprite.png
SklearnYuTensorflowJiqiXuexiShiyongZhinanZhongwenban2018620/img/apple-touch-icon.png
SklearnYuTensorflowJiqiXuexiShiyongZhinanZhongwenban2018620/img/cancelfullscreen.png
SklearnYuTensorflowJiqiXuexiShiyongZhinanZhongwenban2018620/img/close.png
SklearnYuTensorflowJiqiXuexiShiyongZhinanZhongwenban2018620/img/fullscreen.png
SklearnYuTensorflowJiqiXuexiShiyongZhinanZhongwenban2018620/img/loader.gif
SklearnYuTensorflowJiqiXuexiShiyongZhinanZhongwenban2018620/img/menu-icon.png
SklearnYuTensorflowJiqiXuexiShiyongZhinanZhongwenban2018620/img/save.png
sklearn_yu_tensorflow_jiqi_xuexi_shiyong_zhinan_zhongwenban_2018_6_20-2024.3.3.0.dist-info/METADATA
sklearn_yu_tensorflow_jiqi_xuexi_shiyong_zhinan_zhongwenban_2018_6_20-2024.3.3.0.dist-info/WHEEL
sklearn_yu_tensorflow_jiqi_xuexi_shiyong_zhinan_zhongwenban_2018_6_20-2024.3.3.0.dist-info/entry_points.txt
sklearn_yu_tensorflow_jiqi_xuexi_shiyong_zhinan_zhongwenban_2018_6_20-2024.3.3.0.dist-info/top_level.txt
sklearn_yu_tensorflow_jiqi_xuexi_shiyong_zhinan_zhongwenban_2018_6_20-2024.3.3.0.dist-info/RECORD
